azdev/__init__.py
azdev/__main__.py
azdev/commands.py
azdev/completer.py
azdev/help.py
azdev/params.py
azdev/transformers.py
azdev/config/__init__.py
azdev/config/cli.flake8
azdev/config/cli_pylintrc
azdev/config/ext.flake8
azdev/config/ext_pylintrc
azdev/mod_templates/HISTORY.rst
azdev/mod_templates/README.rst
azdev/mod_templates/_client_factory.py
azdev/mod_templates/_help.py
azdev/mod_templates/_params.py
azdev/mod_templates/_validators.py
azdev/mod_templates/azext_metadata.json
azdev/mod_templates/blank__init__.py
azdev/mod_templates/commands.py
azdev/mod_templates/custom.py
azdev/mod_templates/module__init__.py
azdev/mod_templates/pkg_declare__init__.py
azdev/mod_templates/setup.cfg
azdev/mod_templates/setup.py
azdev/mod_templates/test_service_scenario.py
azdev/operations/__init__.py
azdev/operations/code_gen.py
azdev/operations/constant.py
azdev/operations/legal.py
azdev/operations/performance.py
azdev/operations/pypi.py
azdev/operations/python_sdk.py
azdev/operations/regex.py
azdev/operations/resource.py
azdev/operations/secret.py
azdev/operations/setup.py
azdev/operations/style.py
azdev/operations/breaking_change/__init__.py
azdev/operations/breaking_change/markdown_template.jinja2
azdev/operations/cmdcov/__init__.py
azdev/operations/cmdcov/_macros.j2
azdev/operations/cmdcov/cmdcov.py
azdev/operations/cmdcov/component.css
azdev/operations/cmdcov/component.js
azdev/operations/cmdcov/favicon.ico
azdev/operations/cmdcov/index.j2
azdev/operations/cmdcov/index2.j2
azdev/operations/cmdcov/module.j2
azdev/operations/command_change/__init__.py
azdev/operations/command_change/custom.py
azdev/operations/command_change/util.py
azdev/operations/extensions/__init__.py
azdev/operations/extensions/util.py
azdev/operations/extensions/version_upgrade.py
azdev/operations/help/__init__.py
azdev/operations/help/refdoc/__init__.py
azdev/operations/help/refdoc/conf.py
azdev/operations/linter/__init__.py
azdev/operations/linter/linter.py
azdev/operations/linter/rule_decorators.py
azdev-0.2.7.dist-info/licenses/LICENSE
azdev-0.2.7.dist-info/METADATA
azdev-0.2.7.dist-info/WHEEL
azdev-0.2.7.dist-info/entry_points.txt
azdev-0.2.7.dist-info/top_level.txt
azdev-0.2.7.dist-info/RECORD
