Metadata-Version: 2.4
Name: azdev
Version: 0.2.7
Summary: Microsoft Azure CLI Developer Tools
Home-page: https://github.com/Azure/azure-cli-dev-tools
Author: Microsoft Corporation
Author-email: azpycli@microsoft.com
License: MIT
Keywords: azure
Classifier: Development Status :: 5 - Production/Stable
Classifier: Intended Audience :: Developers
Classifier: Topic :: Software Development :: Build Tools
Classifier: Environment :: Console
Classifier: License :: OSI Approved :: MIT License
Classifier: Natural Language :: English
Classifier: Programming Language :: Python :: 3.9
Classifier: Programming Language :: Python :: 3.10
Classifier: Programming Language :: Python :: 3.11
Classifier: Programming Language :: Python :: 3.12
Classifier: Programming Language :: Python :: 3.13
Requires-Python: >=3.9
License-File: LICENSE
Requires-Dist: azure-multiapi-storage
Requires-Dist: docutils
Requires-Dist: flake8
Requires-Dist: gitpython
Requires-Dist: jinja2
Requires-Dist: knack
Requires-Dist: pylint<4
Requires-Dist: pytest-xdist
Requires-Dist: pytest-forked
Requires-Dist: pytest>=5.0.0
Requires-Dist: pyyaml
Requires-Dist: requests
Requires-Dist: sphinx==1.6.7
Requires-Dist: tox
Requires-Dist: jsbeautifier~=1.14.7
Requires-Dist: deepdiff~=8.6.1
Requires-Dist: azure-cli-diff-tool~=0.1.1
Requires-Dist: packaging
Requires-Dist: tqdm
Requires-Dist: wheel==0.30.0
Requires-Dist: setuptools==70.0.0
Requires-Dist: microsoft-security-utilities-secret-masker~=1.0.0b4
Dynamic: author
Dynamic: author-email
Dynamic: classifier
Dynamic: description
Dynamic: home-page
Dynamic: keywords
Dynamic: license
Dynamic: license-file
Dynamic: requires-dist
Dynamic: requires-python
Dynamic: summary
